django_mosql-0.5.1.dist-info/DESCRIPTION.rst
django_mosql-0.5.1.dist-info/METADATA
django_mosql-0.5.1.dist-info/RECORD
django_mosql-0.5.1.dist-info/WHEEL
django_mosql-0.5.1.dist-info/metadata.json
django_mosql-0.5.1.dist-info/top_level.txt
djangomosql/__init__.py
djangomosql/compat.py
djangomosql/functions.py
djangomosql/models.py
djangomosql/utils.py
djangomosql/db/__init__.py
djangomosql/db/handlers.py
djangomosql/db/patch.py
