Metadata-Version: 2.0
Name: django-mosql
Version: 0.5.1
Summary: Django model integration for MoSQL.
Home-page: http://github.com/uranusjr/django-mosql
Author: Tzu-ping Chung
Author-email: uranusjr@gmail.com
License: BSD License
Platform: UNKNOWN
Classifier: Environment :: Web Environment
Classifier: Framework :: Django
Classifier: Intended Audience :: Developers
Classifier: License :: OSI Approved :: BSD License
Classifier: Operating System :: OS Independent
Classifier: Programming Language :: Python
Classifier: Programming Language :: Python :: 2
Classifier: Programming Language :: Python :: 2.7
Classifier: Programming Language :: Python :: 3
Classifier: Programming Language :: Python :: 3.4
Classifier: Topic :: Internet :: WWW/HTTP
Classifier: Topic :: Internet :: WWW/HTTP :: Dynamic Content
Requires-Dist: django (>=1.6)
Requires-Dist: mosql (>=0.8.1,<0.9.1)
